LICENSE
MANIFEST.in
README.rst
changelog
requirements.txt
setup.py
postfind/__init__.py
postfind/debug.py
postfind/finder.py
postfind/run.py
postfind.egg-info/PKG-INFO
postfind.egg-info/SOURCES.txt
postfind.egg-info/dependency_links.txt
postfind.egg-info/entry_points.txt
postfind.egg-info/requires.txt
postfind.egg-info/top_level.txt
postfind.egg-info/zip-safe