Metadata-Version: 1.1
Name: postfind
Version: 0.2.0
Summary: Follow a message (by Message-ID) in postfix logs
Home-page: UNKNOWN
Author: Henrik Levkowetz
Author-email: henrik@levkowetz.com
License: BSD license
Platform: UNKNOWN
Classifier: Development Status :: 4 - Beta
Classifier: Intended Audience :: Developers
Classifier: Topic :: Communications :: Email
Classifier: Topic :: Communications :: Email :: Mail Transport Agents
Classifier: License :: OSI Approved :: BSD License
Classifier: Programming Language :: Python :: 2
Classifier: Programming Language :: Python :: 2.7
